{
    "key": "group_5e309fd94eeb8",
    "title": "WooCommerce - Extra Product Options",
    "fields": [
        {
            "key": "field_5e309fd9a800a",
            "label": "Banner",
            "name": "",
            "type": "tab",
            "instructions": "",
            "required": 0,
            "conditional_logic": 0,
            "wrapper": {
                "width": "",
                "class": "",
                "id": ""
            },
            "placement": "left",
            "endpoint": 0
        },
        {
            "key": "field_5e309fd9a8012",
            "label": "Enable Product Information Banner",
            "name": "woo_product_information_banner",
            "type": "group",
            "instructions": "",
            "required": 0,
            "conditional_logic": 0,
            "wrapper": {
                "width": "",
                "class": "",
                "id": ""
            },
            "layout": "block",
            "sub_fields": [
                {
                    "key": "field_5e309fd9c34a7",
                    "label": "Enable Banner",
                    "name": "enable_banner",
                    "type": "true_false",
                    "instructions": "",
                    "required": 0,
                    "conditional_logic": 0,
                    "wrapper": {
                        "width": "",
                        "class": "",
                        "id": ""
                    },
                    "message": "",
                    "default_value": 0,
                    "ui": 1,
                    "ui_on_text": "",
                    "ui_off_text": ""
                },
                {
                    "key": "field_5e309fd9c34e0",
                    "label": "Banner message",
                    "name": "banner_message",
                    "type": "textarea",
                    "instructions": "Place a back ordered message here",
                    "required": 0,
                    "conditional_logic": [
                        [
                            {
                                "field": "field_5e309fd9c34a7",
                                "operator": "==",
                                "value": "1"
                            }
                        ]
                    ],
                    "wrapper": {
                        "width": "",
                        "class": "",
                        "id": ""
                    },
                    "default_value": "Due To High Demand, this Product is Currently Backordered. We Expect To Resume Shipment on",
                    "placeholder": "",
                    "maxlength": "",
                    "rows": "",
                    "new_lines": ""
                }
            ]
        },
        {
            "key": "field_5e309fd9dc0c8",
            "label": "Features List",
            "name": "",
            "type": "tab",
            "instructions": "",
            "required": 0,
            "conditional_logic": 0,
            "wrapper": {
                "width": "",
                "class": "",
                "id": ""
            },
            "placement": "left",
            "endpoint": 0
        },
        {
            "key": "field_5e309fd9e4273",
            "label": "Features List",
            "name": "woo_product_features_list",
            "type": "repeater",
            "instructions": "A list of items that goes in the faq \/ specs section",
            "required": 0,
            "conditional_logic": 0,
            "wrapper": {
                "width": "",
                "class": "",
                "id": ""
            },
            "collapsed": "",
            "min": 0,
            "max": 0,
            "layout": "table",
            "button_label": "Add Feature",
            "sub_fields": [
                {
                    "key": "field_5e309fd9ec6e4",
                    "label": "Feature",
                    "name": "feature",
                    "type": "text",
                    "instructions": "",
                    "required": 0,
                    "conditional_logic": 0,
                    "wrapper": {
                        "width": "",
                        "class": "",
                        "id": ""
                    },
                    "default_value": "",
                    "placeholder": "",
                    "prepend": "",
                    "append": "",
                    "maxlength": ""
                }
            ]
        },
        {
            "key": "field_5e309fda10231",
            "label": "Frequently Asked Questions",
            "name": "",
            "type": "tab",
            "instructions": "",
            "required": 0,
            "conditional_logic": 0,
            "wrapper": {
                "width": "",
                "class": "",
                "id": ""
            },
            "placement": "left",
            "endpoint": 0
        },
        {
            "key": "field_5e309fda18181",
            "label": "Frequently Asked Questions",
            "name": "woo_product_frequently_asked_questions",
            "type": "repeater",
            "instructions": "Add a title for the question for when it's hidden, and the content for when it's not",
            "required": 0,
            "conditional_logic": 0,
            "wrapper": {
                "width": "",
                "class": "",
                "id": ""
            },
            "collapsed": "",
            "min": 0,
            "max": 0,
            "layout": "table",
            "button_label": "Add FAQ Question",
            "sub_fields": [
                {
                    "key": "field_5e309fda20310",
                    "label": "Question Title",
                    "name": "title",
                    "type": "text",
                    "instructions": "",
                    "required": 1,
                    "conditional_logic": 0,
                    "wrapper": {
                        "width": "",
                        "class": "",
                        "id": ""
                    },
                    "default_value": "",
                    "placeholder": "",
                    "prepend": "",
                    "append": "",
                    "maxlength": ""
                },
                {
                    "key": "field_5e309fda2031b",
                    "label": "Question Answer Content",
                    "name": "content",
                    "type": "wysiwyg",
                    "instructions": "",
                    "required": 1,
                    "conditional_logic": 0,
                    "wrapper": {
                        "width": "",
                        "class": "",
                        "id": ""
                    },
                    "default_value": "",
                    "tabs": "all",
                    "toolbar": "full",
                    "media_upload": 1,
                    "delay": 0
                }
            ]
        },
        {
            "key": "field_5e309fda38e1d",
            "label": "Tri Gallery",
            "name": "",
            "type": "tab",
            "instructions": "",
            "required": 0,
            "conditional_logic": 0,
            "wrapper": {
                "width": "",
                "class": "",
                "id": ""
            },
            "placement": "left",
            "endpoint": 0
        },
        {
            "key": "field_5e30a29d8935f",
            "label": "Enable Tri Gallery",
            "name": "woo_enable_tri_gallery",
            "type": "true_false",
            "instructions": "",
            "required": 0,
            "conditional_logic": 0,
            "wrapper": {
                "width": "",
                "class": "",
                "id": ""
            },
            "message": "",
            "default_value": 0,
            "ui": 1,
            "ui_on_text": "",
            "ui_off_text": ""
        },
        {
            "key": "field_5e309fda43935",
            "label": "Tri Gallery",
            "name": "woo_product_tri_gallery",
            "type": "repeater",
            "instructions": "Allows the user to place 3 images as a sort of product action shot gallery",
            "required": 0,
            "conditional_logic": [
                [
                    {
                        "field": "field_5e30a29d8935f",
                        "operator": "==",
                        "value": "1"
                    }
                ]
            ],
            "wrapper": {
                "width": "",
                "class": "",
                "id": ""
            },
            "collapsed": "",
            "min": 0,
            "max": 3,
            "layout": "table",
            "button_label": "Add Gallery Image",
            "sub_fields": [
                {
                    "key": "field_5e309fda4cb87",
                    "label": "Image",
                    "name": "image",
                    "type": "image",
                    "instructions": "",
                    "required": 0,
                    "conditional_logic": 0,
                    "wrapper": {
                        "width": "",
                        "class": "",
                        "id": ""
                    },
                    "return_format": "id",
                    "preview_size": "thumbnail",
                    "library": "all",
                    "min_width": "",
                    "min_height": "",
                    "min_size": "",
                    "max_width": "",
                    "max_height": "",
                    "max_size": "",
                    "mime_types": ""
                }
            ]
        },
        {
            "key": "field_5e30a5e189366",
            "label": "50\/50 - Image",
            "name": "",
            "type": "tab",
            "instructions": "",
            "required": 0,
            "conditional_logic": 0,
            "wrapper": {
                "width": "",
                "class": "",
                "id": ""
            },
            "placement": "left",
            "endpoint": 0
        },
        {
            "key": "field_5e30a5fd89367",
            "label": "Enable 50\/50 Image",
            "name": "woo_enable_5050_image",
            "type": "true_false",
            "instructions": "",
            "required": 0,
            "conditional_logic": 0,
            "wrapper": {
                "width": "",
                "class": "",
                "id": ""
            },
            "message": "",
            "default_value": 0,
            "ui": 1,
            "ui_on_text": "",
            "ui_off_text": ""
        },
        {
            "key": "field_5e30a61589368",
            "label": "50\/50 - Image",
            "name": "woo_5050_image",
            "type": "repeater",
            "instructions": "",
            "required": 0,
            "conditional_logic": [
                [
                    {
                        "field": "field_5e30a5fd89367",
                        "operator": "==",
                        "value": "1"
                    }
                ]
            ],
            "wrapper": {
                "width": "",
                "class": "",
                "id": ""
            },
            "collapsed": "",
            "min": 0,
            "max": 2,
            "layout": "table",
            "button_label": "",
            "sub_fields": [
                {
                    "key": "field_5e30a64289369",
                    "label": "Title",
                    "name": "title",
                    "type": "text",
                    "instructions": "",
                    "required": 0,
                    "conditional_logic": [
                        [
                            {
                                "field": "field_5e30a5fd89367",
                                "operator": "==",
                                "value": "1"
                            }
                        ]
                    ],
                    "wrapper": {
                        "width": "50",
                        "class": "",
                        "id": ""
                    },
                    "default_value": "",
                    "placeholder": "",
                    "prepend": "",
                    "append": "",
                    "maxlength": ""
                },
                {
                    "key": "field_5e30a6548936a",
                    "label": "Image",
                    "name": "image",
                    "type": "image",
                    "instructions": "",
                    "required": 0,
                    "conditional_logic": [
                        [
                            {
                                "field": "field_5e30a5fd89367",
                                "operator": "==",
                                "value": "1"
                            }
                        ]
                    ],
                    "wrapper": {
                        "width": "50",
                        "class": "",
                        "id": ""
                    },
                    "return_format": "id",
                    "preview_size": "medium",
                    "library": "all",
                    "min_width": "",
                    "min_height": "",
                    "min_size": "",
                    "max_width": "",
                    "max_height": "",
                    "max_size": "",
                    "mime_types": ""
                }
            ]
        },
        {
            "key": "field_5e309fda67961",
            "label": "Hashtag Gallery",
            "name": "",
            "type": "tab",
            "instructions": "",
            "required": 0,
            "conditional_logic": 0,
            "wrapper": {
                "width": "",
                "class": "",
                "id": ""
            },
            "placement": "left",
            "endpoint": 0
        },
        {
            "key": "field_5e30a32789361",
            "label": "Enable Hashtag Gallery",
            "name": "woo_enable_hashtag_gallery",
            "type": "true_false",
            "instructions": "",
            "required": 0,
            "conditional_logic": 0,
            "wrapper": {
                "width": "",
                "class": "",
                "id": ""
            },
            "message": "",
            "default_value": 0,
            "ui": 1,
            "ui_on_text": "",
            "ui_off_text": ""
        },
        {
            "key": "field_5e309fda6fbbd",
            "label": "Hashtag Gallery",
            "name": "woo_proudct_hashtag_gallery",
            "type": "group",
            "instructions": "Choose a text hashtag to associate with a group of user product images",
            "required": 0,
            "conditional_logic": [
                [
                    {
                        "field": "field_5e30a32789361",
                        "operator": "==",
                        "value": "1"
                    }
                ]
            ],
            "wrapper": {
                "width": "",
                "class": "",
                "id": ""
            },
            "layout": "block",
            "sub_fields": [
                {
                    "key": "field_5e309fda77da6",
                    "label": "Hashtag Text",
                    "name": "hashtag_text",
                    "type": "text",
                    "instructions": "Add the text (without a #) to display above the user product image shots",
                    "required": 0,
                    "conditional_logic": 0,
                    "wrapper": {
                        "width": "",
                        "class": "",
                        "id": ""
                    },
                    "default_value": "",
                    "placeholder": "",
                    "prepend": "",
                    "append": "",
                    "maxlength": ""
                },
                {
                    "key": "field_5e309fda77db1",
                    "label": "User Product Images",
                    "name": "product_images",
                    "type": "repeater",
                    "instructions": "The images that show up in the carousel",
                    "required": 0,
                    "conditional_logic": 0,
                    "wrapper": {
                        "width": "",
                        "class": "",
                        "id": ""
                    },
                    "collapsed": "",
                    "min": 1,
                    "max": 0,
                    "layout": "table",
                    "button_label": "",
                    "sub_fields": [
                        {
                            "key": "field_5e309fda8812c",
                            "label": "Image",
                            "name": "image",
                            "type": "image",
                            "instructions": "",
                            "required": 0,
                            "conditional_logic": 0,
                            "wrapper": {
                                "width": "",
                                "class": "",
                                "id": ""
                            },
                            "return_format": "id",
                            "preview_size": "thumbnail",
                            "library": "all",
                            "min_width": "",
                            "min_height": "",
                            "min_size": "",
                            "max_width": "",
                            "max_height": "",
                            "max_size": "",
                            "mime_types": ""
                        }
                    ]
                }
            ]
        },
        {
            "key": "field_5e309fdaa03fb",
            "label": "50\/50 - About Highlight",
            "name": "",
            "type": "tab",
            "instructions": "",
            "required": 0,
            "conditional_logic": 0,
            "wrapper": {
                "width": "",
                "class": "",
                "id": ""
            },
            "placement": "left",
            "endpoint": 0
        },
        {
            "key": "field_5e30a2d689360",
            "label": "Enable 50\/50 - About  Highlight",
            "name": "woo_enable_5050_highlight",
            "type": "true_false",
            "instructions": "",
            "required": 0,
            "conditional_logic": 0,
            "wrapper": {
                "width": "",
                "class": "",
                "id": ""
            },
            "message": "",
            "default_value": 0,
            "ui": 1,
            "ui_on_text": "",
            "ui_off_text": ""
        },
        {
            "key": "field_5e309fdaa8458",
            "label": "50\/50 - About Highlight",
            "name": "woo_product_fifty_fifty_about_highlight",
            "type": "group",
            "instructions": "Add an image and information.",
            "required": 0,
            "conditional_logic": [
                [
                    {
                        "field": "field_5e30a2d689360",
                        "operator": "==",
                        "value": "1"
                    }
                ]
            ],
            "wrapper": {
                "width": "",
                "class": "",
                "id": ""
            },
            "layout": "block",
            "sub_fields": [
                {
                    "key": "field_5e309fdab085a",
                    "label": "Image",
                    "name": "image",
                    "type": "image",
                    "instructions": "",
                    "required": 0,
                    "conditional_logic": 0,
                    "wrapper": {
                        "width": "",
                        "class": "",
                        "id": ""
                    },
                    "return_format": "id",
                    "preview_size": "thumbnail",
                    "library": "all",
                    "min_width": "",
                    "min_height": "",
                    "min_size": "",
                    "max_width": "",
                    "max_height": "",
                    "max_size": "",
                    "mime_types": ""
                },
                {
                    "key": "field_5e309fdab0864",
                    "label": "Content",
                    "name": "content",
                    "type": "wysiwyg",
                    "instructions": "",
                    "required": 0,
                    "conditional_logic": 0,
                    "wrapper": {
                        "width": "",
                        "class": "",
                        "id": ""
                    },
                    "default_value": "",
                    "tabs": "all",
                    "toolbar": "full",
                    "media_upload": 1,
                    "delay": 0
                }
            ]
        },
        {
            "key": "field_5e309fdac91fc",
            "label": "Leather",
            "name": "",
            "type": "tab",
            "instructions": "",
            "required": 0,
            "conditional_logic": 0,
            "wrapper": {
                "width": "",
                "class": "",
                "id": ""
            },
            "placement": "top",
            "endpoint": 0
        },
        {
            "key": "field_5e309fdad159e",
            "label": "Enable Leather",
            "name": "woo_enable_about_the_leather",
            "type": "true_false",
            "instructions": "",
            "required": 0,
            "conditional_logic": 0,
            "wrapper": {
                "width": "",
                "class": "",
                "id": ""
            },
            "message": "",
            "default_value": 0,
            "ui": 1,
            "ui_on_text": "",
            "ui_off_text": ""
        },
        {
            "key": "field_5e57e745b1a28",
            "label": "Leather Image",
            "name": "woo_leather_image",
            "type": "image",
            "instructions": "",
            "required": 0,
            "conditional_logic": [
                [
                    {
                        "field": "field_5e309fdad159e",
                        "operator": "==",
                        "value": "1"
                    }
                ]
            ],
            "wrapper": {
                "width": "",
                "class": "",
                "id": ""
            },
            "return_format": "id",
            "preview_size": "thumbnail",
            "library": "all",
            "min_width": "",
            "min_height": "",
            "min_size": "",
            "max_width": "",
            "max_height": "",
            "max_size": "",
            "mime_types": ""
        },
        {
            "key": "field_5e57f0a87b96c",
            "label": "About Leather Image",
            "name": "woo_leather_image",
            "type": "image",
            "instructions": "",
            "required": 0,
            "conditional_logic": [
                [
                    {
                        "field": "field_5e309fdad159e",
                        "operator": "==",
                        "value": "1"
                    }
                ]
            ],
            "wrapper": {
                "width": "",
                "class": "",
                "id": ""
            },
            "return_format": "id",
            "preview_size": "thumbnail",
            "library": "all",
            "min_width": "",
            "min_height": "",
            "min_size": "",
            "max_width": "",
            "max_height": "",
            "max_size": "",
            "mime_types": ""
        },
        {
            "key": "field_5e30a44489362",
            "label": "Care and Cleaning",
            "name": "",
            "type": "tab",
            "instructions": "",
            "required": 0,
            "conditional_logic": 0,
            "wrapper": {
                "width": "",
                "class": "",
                "id": ""
            },
            "placement": "left",
            "endpoint": 0
        },
        {
            "key": "field_5e30a45c89363",
            "label": "Enable Care and Cleaning",
            "name": "woo_enable_care_and_cleaning",
            "type": "true_false",
            "instructions": "",
            "required": 0,
            "conditional_logic": 0,
            "wrapper": {
                "width": "",
                "class": "",
                "id": ""
            },
            "message": "",
            "default_value": 0,
            "ui": 1,
            "ui_on_text": "",
            "ui_off_text": ""
        },
        {
            "key": "field_5e30a47189364",
            "label": "Title",
            "name": "woo_care_and_cleaning_title",
            "type": "text",
            "instructions": "",
            "required": 0,
            "conditional_logic": [
                [
                    {
                        "field": "field_5e30a45c89363",
                        "operator": "==",
                        "value": "1"
                    }
                ]
            ],
            "wrapper": {
                "width": "50",
                "class": "",
                "id": ""
            },
            "default_value": "",
            "placeholder": "",
            "prepend": "",
            "append": "",
            "maxlength": ""
        },
        {
            "key": "field_5e30a49b89365",
            "label": "Blurb",
            "name": "woo_care_and_cleaning_blurb",
            "type": "textarea",
            "instructions": "",
            "required": 0,
            "conditional_logic": [
                [
                    {
                        "field": "field_5e30a45c89363",
                        "operator": "==",
                        "value": "1"
                    }
                ]
            ],
            "wrapper": {
                "width": "50",
                "class": "",
                "id": ""
            },
            "default_value": "",
            "placeholder": "",
            "maxlength": "",
            "rows": 4,
            "new_lines": "br"
        },
        {
            "key": "field_5e30a8408936b",
            "label": "50\/50 - Text",
            "name": "",
            "type": "tab",
            "instructions": "",
            "required": 0,
            "conditional_logic": 0,
            "wrapper": {
                "width": "",
                "class": "",
                "id": ""
            },
            "placement": "left",
            "endpoint": 0
        },
        {
            "key": "field_5e30a8818936c",
            "label": "Enable 50\/50 - Text",
            "name": "enable_fifty_fifty_text",
            "type": "true_false",
            "instructions": "",
            "required": 0,
            "conditional_logic": 0,
            "wrapper": {
                "width": "",
                "class": "",
                "id": ""
            },
            "message": "",
            "default_value": 0,
            "ui": 1,
            "ui_on_text": "",
            "ui_off_text": ""
        },
        {
            "key": "field_5e30a8a48936d",
            "label": "50\/50 - Text",
            "name": "woo_product_fifty_fifty_text",
            "type": "repeater",
            "instructions": "",
            "required": 0,
            "conditional_logic": [
                [
                    {
                        "field": "field_5e30a8818936c",
                        "operator": "==",
                        "value": "1"
                    }
                ]
            ],
            "wrapper": {
                "width": "",
                "class": "",
                "id": ""
            },
            "collapsed": "",
            "min": 0,
            "max": 0,
            "layout": "table",
            "button_label": "",
            "sub_fields": [
                {
                    "key": "field_5e30a8e98936e",
                    "label": "Title",
                    "name": "title",
                    "type": "text",
                    "instructions": "",
                    "required": 0,
                    "conditional_logic": 0,
                    "wrapper": {
                        "width": "50",
                        "class": "",
                        "id": ""
                    },
                    "default_value": "",
                    "placeholder": "",
                    "prepend": "",
                    "append": "",
                    "maxlength": ""
                },
                {
                    "key": "field_5e30a8f18936f",
                    "label": "Blurb",
                    "name": "blurb",
                    "type": "wysiwyg",
                    "instructions": "",
                    "required": 0,
                    "conditional_logic": 0,
                    "wrapper": {
                        "width": "50",
                        "class": "",
                        "id": ""
                    },
                    "default_value": "",
                    "tabs": "all",
                    "toolbar": "full",
                    "media_upload": 1,
                    "delay": 0
                }
            ]
        },
        {
            "key": "field_5e309fdad9901",
            "label": "Similar, Also in this collection, Pairs well with",
            "name": "",
            "type": "tab",
            "instructions": "",
            "required": 0,
            "conditional_logic": 0,
            "wrapper": {
                "width": "",
                "class": "",
                "id": ""
            },
            "placement": "left",
            "endpoint": 0
        },
        {
            "key": "field_5e30a9bd89371",
            "label": "Enable Similar, Also in this collection, Pairs well with",
            "name": "woo_enable_similar_pairs_well_with",
            "type": "true_false",
            "instructions": "",
            "required": 0,
            "conditional_logic": 0,
            "wrapper": {
                "width": "",
                "class": "",
                "id": ""
            },
            "message": "",
            "default_value": 0,
            "ui": 1,
            "ui_on_text": "",
            "ui_off_text": ""
        },
        {
            "key": "field_5e309fdae1b94",
            "label": "Similar, Also in this collection, Pairs well with",
            "name": "woo_product_other_product_associations",
            "type": "group",
            "instructions": "Used for the similar, also in this collection, and pairs well with",
            "required": 0,
            "conditional_logic": [
                [
                    {
                        "field": "field_5e30a9bd89371",
                        "operator": "==",
                        "value": "1"
                    }
                ]
            ],
            "wrapper": {
                "width": "",
                "class": "",
                "id": ""
            },
            "layout": "block",
            "sub_fields": [
                {
                    "key": "field_5e309fdaea15f",
                    "label": "Similar Products",
                    "name": "similar_products",
                    "type": "repeater",
                    "instructions": "",
                    "required": 0,
                    "conditional_logic": 0,
                    "wrapper": {
                        "width": "",
                        "class": "",
                        "id": ""
                    },
                    "collapsed": "",
                    "min": 1,
                    "max": 0,
                    "layout": "table",
                    "button_label": "Add Product",
                    "sub_fields": [
                        {
                            "key": "field_5e309fdaf2949",
                            "label": "Product",
                            "name": "product",
                            "type": "relationship",
                            "instructions": "",
                            "required": 0,
                            "conditional_logic": 0,
                            "wrapper": {
                                "width": "",
                                "class": "",
                                "id": ""
                            },
                            "post_type": [
                                "product"
                            ],
                            "taxonomy": [],
                            "filters": [
                                "search",
                                "post_type",
                                "taxonomy"
                            ],
                            "elements": "",
                            "min": "",
                            "max": "",
                            "return_format": ""
                        }
                    ]
                },
                {
                    "key": "field_5e309fdb0ea85",
                    "label": "Also In This Collection Products",
                    "name": "also_in_products",
                    "type": "repeater",
                    "instructions": "",
                    "required": 0,
                    "conditional_logic": 0,
                    "wrapper": {
                        "width": "",
                        "class": "",
                        "id": ""
                    },
                    "collapsed": "",
                    "min": 1,
                    "max": 0,
                    "layout": "table",
                    "button_label": "Add Product",
                    "sub_fields": [
                        {
                            "key": "field_5e309fdb16be4",
                            "label": "Product",
                            "name": "product",
                            "type": "relationship",
                            "instructions": "",
                            "required": 0,
                            "conditional_logic": 0,
                            "wrapper": {
                                "width": "",
                                "class": "",
                                "id": ""
                            },
                            "post_type": [
                                "product"
                            ],
                            "taxonomy": [],
                            "filters": [
                                "search",
                                "post_type",
                                "taxonomy"
                            ],
                            "elements": "",
                            "min": "",
                            "max": "",
                            "return_format": ""
                        }
                    ]
                },
                {
                    "key": "field_5e309fdb271e8",
                    "label": "Pairs Well With Products",
                    "name": "pairs_well_with_products",
                    "type": "repeater",
                    "instructions": "",
                    "required": 0,
                    "conditional_logic": 0,
                    "wrapper": {
                        "width": "",
                        "class": "",
                        "id": ""
                    },
                    "collapsed": "",
                    "min": 1,
                    "max": 0,
                    "layout": "table",
                    "button_label": "Add Product",
                    "sub_fields": [
                        {
                            "key": "field_5e309fdb2f5e4",
                            "label": "Product",
                            "name": "product",
                            "type": "relationship",
                            "instructions": "",
                            "required": 0,
                            "conditional_logic": 0,
                            "wrapper": {
                                "width": "",
                                "class": "",
                                "id": ""
                            },
                            "post_type": [
                                "product"
                            ],
                            "taxonomy": [],
                            "filters": [
                                "search",
                                "post_type",
                                "taxonomy"
                            ],
                            "elements": "",
                            "min": "",
                            "max": "",
                            "return_format": "object"
                        }
                    ]
                }
            ]
        },
        {
            "key": "field_5e30a97589370",
            "label": "Show Top Border",
            "name": "woo_product_other_product_associations_border",
            "type": "true_false",
            "instructions": "",
            "required": 0,
            "conditional_logic": [
                [
                    {
                        "field": "field_5e30a9bd89371",
                        "operator": "==",
                        "value": "1"
                    }
                ]
            ],
            "wrapper": {
                "width": "",
                "class": "",
                "id": ""
            },
            "message": "",
            "default_value": 0,
            "ui": 1,
            "ui_on_text": "",
            "ui_off_text": ""
        },
        {
            "key": "field_5e3323179f9c2",
            "label": "Retail Dimensions",
            "name": "",
            "type": "tab",
            "instructions": "",
            "required": 0,
            "conditional_logic": 0,
            "wrapper": {
                "width": "",
                "class": "",
                "id": ""
            },
            "placement": "top",
            "endpoint": 0
        },
        {
            "key": "field_5e3323549f9c3",
            "label": "Enable Dimensions",
            "name": "woo_enable_dimensions",
            "type": "true_false",
            "instructions": "",
            "required": 0,
            "conditional_logic": 0,
            "wrapper": {
                "width": "",
                "class": "",
                "id": ""
            },
            "message": "",
            "default_value": 0,
            "ui": 1,
            "ui_on_text": "",
            "ui_off_text": ""
        },
        {
            "key": "field_5e3323929f9c4",
            "label": "Content",
            "name": "retail_dimensions",
            "type": "textarea",
            "instructions": "",
            "required": 0,
            "conditional_logic": 0,
            "wrapper": {
                "width": "",
                "class": "",
                "id": ""
            },
            "default_value": "",
            "placeholder": "",
            "maxlength": "",
            "rows": "",
            "new_lines": "wpautop"
        }
    ],
    "location": [
        [
            {
                "param": "post_type",
                "operator": "==",
                "value": "product"
            }
        ]
    ],
    "menu_order": 0,
    "position": "normal",
    "style": "default",
    "label_placement": "top",
    "instruction_placement": "label",
    "hide_on_screen": "",
    "active": 1,
    "description": "",
    "modified": 1582833404
}